[{"id":"d8e1667.b08a598","type":"tab","label":"Make Bucket and Add All photos In it","disabled":false,"info":""},{"id":"aab8a7d1.484548","type":"tab","label":"Make 2 more separated Buckets one for Cats and one for Dogs","disabled":false,"info":""},{"id":"bdba89a3.7c8ec8","type":"tab","label":"Get Presigned URLs","disabled":false,"info":""},{"id":"bc2ca35.71ef96","type":"minio-config","name":"MinIO Instance","host":"127.0.0.1","port":"9000","useSsl":false},{"id":"314660d7.ded97","type":"inject","z":"d8e1667.b08a598","name":"","props":[{"p":"payload"},{"p":"topic","vt":"str"}],"repeat":"","crontab":"","once":false,"onceDelay":0.1,"topic":"","payload":"","payloadType":"date","x":140,"y":120,"wires":[["4b11f987.db9128","7248aa84.04bcf4","fde82c49.aaf8e","455ea3b6.84878c","32444a2b.5f4e06"]]},{"id":"4b11f987.db9128","type":"buckets","z":"d8e1667.b08a598","buckets_name":"Make Bucket \"random-photos\"","host":"bc2ca35.71ef96","buckets_operation":"makeBucket","buckets_bucket":"random-photos","buckets_region":"","buckets_prefix":"","buckets_recursive":false,"buckets_start_after":"","x":380,"y":120,"wires":[["9781fccb.125f3"],["dbb43ff.26e4ac"]]},{"id":"9781fccb.125f3","type":"debug","z":"d8e1667.b08a598","name":"","active":true,"tosidebar":true,"console":false,"tostatus":false,"complete":"false","statusVal":"","statusType":"auto","x":520,"y":80,"wires":[]},{"id":"dbb43ff.26e4ac","type":"debug","z":"d8e1667.b08a598","name":"","active":true,"tosidebar":true,"console":false,"tostatus":false,"complete":"false","statusVal":"","statusType":"auto","x":530,"y":160,"wires":[]},{"id":"370409df.481b66","type":"files","z":"d8e1667.b08a598","files_name":"Upload Random Photos to Minio","host":"bc2ca35.71ef96","files_operation":"fPutObject","files_bucket":"random-photos","files_object":"photo1.jpg","files_filepath":"C:\\Users\\Χαρά\\Desktop\\pics\\photo1.jpg","files_metadata":"","x":430,"y":220,"wires":[["e303e439.01ea98"],[]]},{"id":"e303e439.01ea98","type":"debug","z":"d8e1667.b08a598","name":"","active":true,"tosidebar":true,"console":false,"tostatus":false,"complete":"false","statusVal":"","statusType":"auto","x":690,"y":220,"wires":[]},{"id":"d8b822f7.b43d4","type":"files","z":"d8e1667.b08a598","files_name":"Upload Random Photos to Minio","host":"bc2ca35.71ef96","files_operation":"fPutObject","files_bucket":"random-photos","files_object":"photo2.jpg","files_filepath":"C:\\Users\\Χαρά\\Desktop\\pics\\photo2.jpg","files_metadata":"","x":430,"y":300,"wires":[["6b3338f8.32fe58"],[]]},{"id":"6b3338f8.32fe58","type":"debug","z":"d8e1667.b08a598","name":"","active":true,"tosidebar":true,"console":false,"tostatus":false,"complete":"false","statusVal":"","statusType":"auto","x":690,"y":300,"wires":[]},{"id":"368a4e67.b7cff2","type":"files","z":"d8e1667.b08a598","files_name":"Upload Random Photos to Minio","host":"bc2ca35.71ef96","files_operation":"fPutObject","files_bucket":"random-photos","files_object":"photo3.jpg","files_filepath":"C:\\Users\\Χαρά\\Desktop\\pics\\photo3.jpg","files_metadata":"","x":430,"y":380,"wires":[["660646aa.e7fcc8"],[]]},{"id":"660646aa.e7fcc8","type":"debug","z":"d8e1667.b08a598","name":"","active":true,"tosidebar":true,"console":false,"tostatus":false,"complete":"false","statusVal":"","statusType":"auto","x":690,"y":380,"wires":[]},{"id":"180cf479.22f4dc","type":"files","z":"d8e1667.b08a598","files_name":"Upload Random Photos to Minio","host":"bc2ca35.71ef96","files_operation":"fPutObject","files_bucket":"random-photos","files_object":"photo4.jpg","files_filepath":"C:\\Users\\Χαρά\\Desktop\\pics\\photo4.jpg","files_metadata":"","x":430,"y":460,"wires":[["440e723c.e7085c"],[]]},{"id":"440e723c.e7085c","type":"debug","z":"d8e1667.b08a598","name":"","active":true,"tosidebar":true,"console":false,"tostatus":false,"complete":"false","statusVal":"","statusType":"auto","x":690,"y":460,"wires":[]},{"id":"7248aa84.04bcf4","type":"function","z":"d8e1667.b08a598","name":"Add MetaData","func":"msg.metaData={'x-amz-meta-photonumber': '1'};\nreturn msg;","outputs":1,"noerr":0,"initialize":"","finalize":"","libs":[],"x":220,"y":260,"wires":[["370409df.481b66"]]},{"id":"fde82c49.aaf8e","type":"function","z":"d8e1667.b08a598","name":"Add MetaData","func":"msg.metaData={'x-amz-meta-photonumber': '2'};\nreturn msg;","outputs":1,"noerr":0,"initialize":"","finalize":"","libs":[],"x":220,"y":340,"wires":[["d8b822f7.b43d4"]]},{"id":"455ea3b6.84878c","type":"function","z":"d8e1667.b08a598","name":"Add MetaData","func":"msg.metaData={'x-amz-meta-photonumber': '3'};\nreturn msg;","outputs":1,"noerr":0,"initialize":"","finalize":"","libs":[],"x":220,"y":420,"wires":[["368a4e67.b7cff2"]]},{"id":"32444a2b.5f4e06","type":"function","z":"d8e1667.b08a598","name":"Add MetaData","func":"msg.metaData={'x-amz-meta-photonumber': '4'};\nreturn msg;","outputs":1,"noerr":0,"initialize":"","finalize":"","libs":[],"x":230,"y":500,"wires":[["180cf479.22f4dc"]]},{"id":"120848ab.c9e507","type":"inject","z":"aab8a7d1.484548","name":"","props":[{"p":"payload"},{"p":"topic","vt":"str"}],"repeat":"","crontab":"","once":false,"onceDelay":0.1,"topic":"","payload":"","payloadType":"date","x":160,"y":100,"wires":[["427b6911.4dfa58","de0a5897.4d43e8"]]},{"id":"427b6911.4dfa58","type":"buckets","z":"aab8a7d1.484548","buckets_name":"Make Bucket \"cats\"","host":"bc2ca35.71ef96","buckets_operation":"makeBucket","buckets_bucket":"cats","buckets_region":"","buckets_prefix":"","buckets_recursive":false,"buckets_start_after":"","x":360,"y":100,"wires":[["4410cc29.837aa4"],["f58447e7.ea3fa8"]]},{"id":"4410cc29.837aa4","type":"debug","z":"aab8a7d1.484548","name":"","active":true,"tosidebar":true,"console":false,"tostatus":false,"complete":"false","statusVal":"","statusType":"auto","x":540,"y":60,"wires":[]},{"id":"f58447e7.ea3fa8","type":"debug","z":"aab8a7d1.484548","name":"","active":true,"tosidebar":true,"console":false,"tostatus":false,"complete":"false","statusVal":"","statusType":"auto","x":550,"y":140,"wires":[]},{"id":"de0a5897.4d43e8","type":"buckets","z":"aab8a7d1.484548","buckets_name":"Make Bucket \"dogs\"","host":"bc2ca35.71ef96","buckets_operation":"makeBucket","buckets_bucket":"dogs","buckets_region":"","buckets_prefix":"","buckets_recursive":false,"buckets_start_after":"","x":370,"y":300,"wires":[["51bf04d8.1d4c5c"],["98783a30.01cb08"]]},{"id":"51bf04d8.1d4c5c","type":"debug","z":"aab8a7d1.484548","name":"","active":true,"tosidebar":true,"console":false,"tostatus":false,"complete":"false","statusVal":"","statusType":"auto","x":550,"y":260,"wires":[]},{"id":"98783a30.01cb08","type":"debug","z":"aab8a7d1.484548","name":"","active":true,"tosidebar":true,"console":false,"tostatus":false,"complete":"false","statusVal":"","statusType":"auto","x":550,"y":340,"wires":[]},{"id":"c089706e.823f9","type":"inject","z":"bdba89a3.7c8ec8","name":"","props":[{"p":"payload"},{"p":"topic","vt":"str"}],"repeat":"","crontab":"","once":false,"onceDelay":0.1,"topic":"","payload":"","payloadType":"date","x":170,"y":100,"wires":[["20507f5.4fd2b8","eb8917a6.da3fc8","a2135c1e.0d3ad","71b73997.5d6118"]]},{"id":"20507f5.4fd2b8","type":"presigned","z":"bdba89a3.7c8ec8","presigned_name":"Get Presigned Obj 1","host":"bc2ca35.71ef96","presigned_operation":"presignedGetObject","presigned_bucket":"random-photos","presigned_object":"photo1.jpg","presigned_expiry":"100","presigned_req_params":"","presigned_resp_headers":"","presigned_issue":"","presigned_policy_bucket":"","presigned_policy_key":"","presigned_policy_key_prefix":"","presigned_policy_expires":"","presigned_policy_content_type":"","presigned_policy_content_length_range_from":"","presigned_policy_content_length_range_to":"","x":380,"y":100,"wires":[["e83cc9cf.24df98"],["35acc633.43044a"]]},{"id":"e83cc9cf.24df98","type":"debug","z":"bdba89a3.7c8ec8","name":"","active":true,"tosidebar":true,"console":false,"tostatus":false,"complete":"false","statusVal":"","statusType":"auto","x":630,"y":80,"wires":[]},{"id":"35acc633.43044a","type":"debug","z":"bdba89a3.7c8ec8","name":"","active":true,"tosidebar":true,"console":false,"tostatus":false,"complete":"false","statusVal":"","statusType":"auto","x":630,"y":160,"wires":[]},{"id":"eb8917a6.da3fc8","type":"presigned","z":"bdba89a3.7c8ec8","presigned_name":"Get Presigned Obj 2","host":"bc2ca35.71ef96","presigned_operation":"presignedGetObject","presigned_bucket":"random-photos","presigned_object":"photo2.jpg","presigned_expiry":"100","presigned_req_params":"","presigned_resp_headers":"","presigned_issue":"","presigned_policy_bucket":"","presigned_policy_key":"","presigned_policy_key_prefix":"","presigned_policy_expires":"","presigned_policy_content_type":"","presigned_policy_content_length_range_from":"","presigned_policy_content_length_range_to":"","x":370,"y":220,"wires":[["70c4b65c.4846f8"],["fe2a4aca.d122c8"]]},{"id":"70c4b65c.4846f8","type":"debug","z":"bdba89a3.7c8ec8","name":"","active":true,"tosidebar":true,"console":false,"tostatus":false,"complete":"false","statusVal":"","statusType":"auto","x":620,"y":200,"wires":[]},{"id":"fe2a4aca.d122c8","type":"debug","z":"bdba89a3.7c8ec8","name":"","active":true,"tosidebar":true,"console":false,"tostatus":false,"complete":"false","statusVal":"","statusType":"auto","x":620,"y":280,"wires":[]},{"id":"a2135c1e.0d3ad","type":"presigned","z":"bdba89a3.7c8ec8","presigned_name":"Get Presigned Obj 3","host":"bc2ca35.71ef96","presigned_operation":"presignedGetObject","presigned_bucket":"random-photos","presigned_object":"photo3.jpg","presigned_expiry":"100","presigned_req_params":"","presigned_resp_headers":"","presigned_issue":"","presigned_policy_bucket":"","presigned_policy_key":"","presigned_policy_key_prefix":"","presigned_policy_expires":"","presigned_policy_content_type":"","presigned_policy_content_length_range_from":"","presigned_policy_content_length_range_to":"","x":370,"y":340,"wires":[["d9aeffb.c0bd2"],["d6b97af2.8a8428"]]},{"id":"d9aeffb.c0bd2","type":"debug","z":"bdba89a3.7c8ec8","name":"","active":true,"tosidebar":true,"console":false,"tostatus":false,"complete":"false","statusVal":"","statusType":"auto","x":620,"y":320,"wires":[]},{"id":"d6b97af2.8a8428","type":"debug","z":"bdba89a3.7c8ec8","name":"","active":true,"tosidebar":true,"console":false,"tostatus":false,"complete":"false","statusVal":"","statusType":"auto","x":620,"y":400,"wires":[]},{"id":"71b73997.5d6118","type":"presigned","z":"bdba89a3.7c8ec8","presigned_name":"Get Presigned Obj 4","host":"bc2ca35.71ef96","presigned_operation":"presignedGetObject","presigned_bucket":"random-photos","presigned_object":"photo4.jpg","presigned_expiry":"100","presigned_req_params":"","presigned_resp_headers":"","presigned_issue":"","presigned_policy_bucket":"","presigned_policy_key":"","presigned_policy_key_prefix":"","presigned_policy_expires":"","presigned_policy_content_type":"","presigned_policy_content_length_range_from":"","presigned_policy_content_length_range_to":"","x":370,"y":460,"wires":[["92b45314.07cfa"],["a7555489.0549f8"]]},{"id":"92b45314.07cfa","type":"debug","z":"bdba89a3.7c8ec8","name":"","active":true,"tosidebar":true,"console":false,"tostatus":false,"complete":"false","statusVal":"","statusType":"auto","x":620,"y":440,"wires":[]},{"id":"a7555489.0549f8","type":"debug","z":"bdba89a3.7c8ec8","name":"","active":true,"tosidebar":true,"console":false,"tostatus":false,"complete":"false","statusVal":"","statusType":"auto","x":620,"y":520,"wires":[]}]